pytextrank/__init__.py
pytextrank/base.py
pytextrank/biasedrank.py
pytextrank/positionrank.py
pytextrank/topicrank.py
pytextrank/util.py
pytextrank/version.py
pytextrank-3.3.0.dist-info/LICENSE
pytextrank-3.3.0.dist-info/METADATA
pytextrank-3.3.0.dist-info/WHEEL
pytextrank-3.3.0.dist-info/top_level.txt
pytextrank-3.3.0.dist-info/RECORD
