Metadata-Version: 2.1
Name: pytextrank
Version: 3.3.0
Summary: Python implementation of TextRank as a spaCy pipeline extension, for graph-based natural language work plus related knowledge graph practices; used for for phrase extraction of text documents.
Author-email: "derwen.ai" <info@derwen.ai>
License: MIT License
Project-URL: home, https://derwen.ai/docs/ptr/
Project-URL: DOI, https://doi.org/10.5281/zenodo.4637885
Project-URL: code, http://github.com/DerwenAI/pytextrank
Project-URL: forum, https://www.linkedin.com/groups/6725785/
Project-URL: issues, https://github.com/DerwenAI/pytextrank/issues
Project-URL: spaCy_uniVerse, https://spacy.io/universe/project/spacy-pytextrank
Project-URL: StackOverflow, https://stackoverflow.com/search?q=pytextrank
Project-URL: citations, https://scholar.google.com/scholar?q=related:5tl6J4xZlCIJ:scholar.google.com/&scioq=&hl=en&as_sdt=0,5
Classifier: Development Status :: 5 - Production/Stable
Classifier: License :: OSI Approved :: MIT License
Classifier: Natural Language :: English
Classifier: Intended Audience :: Developers
Classifier: Intended Audience :: Education
Classifier: Intended Audience :: Information Technology
Classifier: Intended Audience :: Science/Research
Classifier: Topic :: Scientific/Engineering :: Artificial Intelligence
Classifier: Topic :: Scientific/Engineering :: Human Machine Interfaces
Classifier: Topic :: Scientific/Engineering :: Information Analysis
Classifier: Topic :: Scientific/Engineering :: Visualization
Classifier: Topic :: Software Development :: Libraries :: Python Modules
Classifier: Topic :: Text Processing :: General
Classifier: Topic :: Text Processing :: Indexing
Classifier: Topic :: Text Processing :: Linguistic
Classifier: Operating System :: OS Independent
Classifier: Programming Language :: Python :: 3
Requires-Python: >=3.7
Provides-Extra: dev
Provides-Extra: test
Provides-Extra: demo
License-File: LICENSE
